cutter/__init__.py
cutter/utils.py
cutter-0.5.0.dist-info/DESCRIPTION.rst
cutter-0.5.0.dist-info/METADATA
cutter-0.5.0.dist-info/RECORD
cutter-0.5.0.dist-info/WHEEL
cutter-0.5.0.dist-info/metadata.json
cutter-0.5.0.dist-info/top_level.txt
test/__init__.py
test/test__init__.py
test/test_utils.py
