Metadata-Version: 1.1
Name: cutter
Version: 0.5.0
Summary: Python list cutter tool
Home-page: UNKNOWN
Author: Florian Mounier
Author-email: paradoxxx.zero@gmail.com
License: UNKNOWN
Platform: Any
Classifier: Development Status :: 4 - Beta
Classifier: Intended Audience :: Developers
Classifier: Operating System :: OS Independent
Classifier: Programming Language :: Python :: 2
Classifier: Programming Language :: Python :: 3
Provides: cutter
